create_cohere_connector/__init__.py
create_cohere_connector/_templates_/.gitignore.jinja
create_cohere_connector/_templates_/app.py.jinja
create_cohere_connector/_templates_/client.py.jinja
create_cohere_connector/_templates_/config.py.jinja
create_cohere_connector/_templates_/datamodels.py.jinja
create_cohere_connector/_templates_/deploy_template.py.jinja
create_cohere_connector/_templates_/env_template.jinja
create_cohere_connector/_templates_/exceptions.py.jinja
create_cohere_connector/_templates_/project_template.py.jinja
create_cohere_connector/_templates_/provider.py.jinja
create_cohere_connector/_templates_/README.md.jinja
create_cohere_connector/cli.py
create_cohere_connector/scaffold.py
create_cohere_connector-0.1.12.dist-info/entry_points.txt
create_cohere_connector-0.1.12.dist-info/LICENSE
create_cohere_connector-0.1.12.dist-info/METADATA
create_cohere_connector-0.1.12.dist-info/WHEEL
create_cohere_connector-0.1.12.dist-info/RECORD
