Metadata-Version: 2.1
Name: create-cohere-connector
Version: 0.1.12
Summary: Scaffold a custom Cohere connector
License: Apache 2.0
Author: dcarpintero
Requires-Python: >=3.12,<4.0
Classifier: License :: Other/Proprietary License
Classifier: Programming Language :: Python :: 3
Classifier: Programming Language :: Python :: 3.12
Requires-Dist: Jinja2 (>=3.1.3,<4.0.0)
Requires-Dist: typer (>=0.9.0,<0.10.0)
